{"stats":{"minecraft:used":{"spartanweaponry:copper_javelin":2,"minecraft:iron_shovel":102,"minecraft:ladder":21,"minecraft:chest":11,"minecraft:shield":8,"minecraft:stone":8,"spartanweaponry:diamond_parrying_dagger":1,"minecraft:soul_sand":2,"spartanweaponry:iron_javelin":27,"securitycraft:keypad_item":1,"spartanweaponry:diamond_rapier":1,"minecraft:tuff":12,"minecraft:glass":2,"minecraft:black_stained_glass_pane":29,"minecraft:lantern":9,"minecraft:red_carpet":3,"minecraft:furnace":8,"minecraft:skeleton_skull":2,"minecraft:potato":752,"minecraft:deepslate_brick_wall":5,"minecraft:damaged_anvil":1,"minecraft:diorite":5,"minecraft:diamond_boots":1,"minecraft:wither_skeleton_skull":1,"minecraft:oak_planks":12,"minecraft:gray_carpet":3,"minecraft:sandstone":5,"minecraft:sand":2,"minecraft:blast_furnace":3,"minecraft:black_banner":15,"minecraft:loom":1,"spartanweaponry:spider_head":6,"minecraft:deepslate_tiles":136,"spartanweaponry:diamond_scythe":673,"minecraft:cyan_bed":7,"minecraft:cyan_carpet":74,"minecraft:gravel":1,"minecraft:soul_lantern":30,"minecraft:nether_wart_block":11,"minecraft:wooden_sword":59,"spartanweaponry:diamond_longbow":102,"minecraft:birch_log":13,"spartanweaponry:iron_scythe":8,"minecraft:chain":14,"minecraft:oak_boat":2,"minecraft:cherry_boat":3,"minecraft:oak_trapdoor":13,"minecraft:enchanting_table":3,"minecraft:stone_sword":18,"minecraft:flint_and_steel":37,"minecraft:armor_stand":1,"minecraft:tinted_glass":4,"minecraft:stone_hoe":2,"minecraft:netherrack":34,"minecraft:torch":11,"spartanweaponry:enderman_head":8,"minecraft:dirt":76,"minecraft:anvil":1,"minecraft:chainmail_chestplate":1,"minecraft:spruce_stairs":1,"minecraft:diamond_helmet":2,"minecraft:granite":18,"minecraft:iron_hoe":1,"minecraft:dark_oak_planks":7,"spartanweaponry:iron_tomahawk":10,"minecraft:iron_axe":257,"luckys_armory:heavy_diamond_armor_helmet":1,"minecraft:crimson_planks":74,"minecraft:barrel":16,"minecraft:smooth_basalt":2,"minecraft:cobbled_deepslate":107,"minecraft:crimson_stem":5,"minecraft:cobbled_deepslate_wall":13,"minecraft:calcite":2,"minecraft:water_bucket":59,"minecraft:amethyst_block":1,"minecraft:cyan_candle":68,"minecraft:baked_potato":250,"minecraft:birch_boat":1,"securitycraft:reinforced_iron_trapdoor":1,"minecraft:stonecutter":3,"minecraft:deepslate_bricks":32,"minecraft:music_disc_cat":3,"minecraft:oak_slab":3,"minecraft:crafting_table":13,"minecraft:birch_sign":3,"minecraft:white_bed":15,"minecraft:dark_oak_door":1,"minecraft:painting":2,"minecraft:cake":2,"minecraft:smoker":2,"minecraft:deepslate_tile_wall":27,"minecraft:flower_pot":1,"minecraft:diamond_pickaxe":1362,"minecraft:iron_pickaxe":2,"minecraft:spruce_pressure_plate":1,"minecraft:stone_slab":3,"minecraft:chiseled_stone_bricks":1,"minecraft:cobblestone":225,"minecraft:potion":1,"minecraft:cobbled_deepslate_slab":34,"minecraft:white_banner":2,"minecraft:cooked_porkchop":4,"minecraft:red_banner":3,"minecraft:bucket":59,"minecraft:pumpkin_pie":4,"minecraft:smooth_stone":1,"minecraft:diamond_leggings":1,"minecraft:jukebox":2,"spartanshields:obsidian_tower_shield":329},"minecraft:custom":{"minecraft:interact_with_crafting_table":120,"minecraft:open_barrel":405,"minecraft:eat_cake_slice":1,"minecraft:leave_game":13,"minecraft:time_since_death":112829,"minecraft:sprint_one_cm":1131278,"minecraft:damage_blocked_by_shield":26341,"minecraft:drop":345,"minecraft:play_noteblock":1,"minecraft:talked_to_villager":5,"minecraft:play_time":924758,"minecraft:deaths":29,"minecraft:jump":8916,"minecraft:walk_on_water_one_cm":103474,"minecraft:interact_with_furnace":132,"minecraft:play_record":3,"minecraft:interact_with_loom":15,"minecraft:sleep_in_bed":17,"minecraft:damage_dealt":50353,"minecraft:player_kills":2,"minecraft:crouch_one_cm":101461,"minecraft:horse_one_cm":276317,"minecraft:interact_with_smoker":22,"minecraft:interact_with_anvil":7,"minecraft:mob_kills":277,"minecraft:damage_dealt_resisted":488,"minecraft:climb_one_cm":135705,"minecraft:walk_one_cm":1613431,"minecraft:damage_dealt_absorbed":80,"minecraft:sneak_time":46593,"minecraft:walk_under_water_one_cm":95012,"minecraft:boat_one_cm":1116800,"minecraft:interact_with_blast_furnace":27,"minecraft:total_world_time":924758,"spartanshields:shield_bash_hits":28,"minecraft:tune_noteblock":28,"minecraft:pot_flower":1,"minecraft:interact_with_stonecutter":25,"minecraft:time_since_rest":113082,"minecraft:damage_taken":19240,"minecraft:swim_one_cm":193785,"minecraft:fly_one_cm":1033810,"minecraft:open_chest":323,"minecraft:fall_one_cm":157989},"minecraft:dropped":{"sophisticatedbackpacks:iron_backpack":1,"minecraft:acacia_boat":1,"minecraft:iron_sword":1,"minecraft:soul_sand":18,"minecraft:birch_planks":1,"minecraft:porkchop":4,"minecraft:oak_log":12,"minecraft:baked_potato":142,"minecraft:glass_bottle":3,"minecraft:diamond":25,"minecraft:dark_oak_slab":1,"minecraft:weeping_vines":1,"minecraft:glow_berries":1,"minecraft:lantern":1,"minecraft:leather":1,"minecraft:leather_helmet":1,"minecraft:emerald":27,"minecraft:cobblestone_stairs":2,"immersive_armors:steampunk_chestplate":1,"minecraft:dirt":72,"luckys_armory:heavy_iron_armor_leggings":1,"minecraft:mutton":4,"minecraft:crimson_roots":2,"alexsmobs:flying_fish":1,"gravestone:obituary":41,"minecraft:pumpkin_pie":34,"minecraft:phantom_membrane":1,"minecraft:sand":11,"minecraft:glistering_melon_slice":2,"minecraft:iron_pickaxe":4,"minecraft:dark_oak_planks":5,"minecraft:birch_log":19,"minecraft:gold_ingot":91,"minecraft:bone":30,"minecraft:gravel":8,"minecraft:oak_door":2,"minecraft:sugar_cane":12,"minecraft:cobbled_deepslate":9,"minecraft:birch_sapling":1,"minecraft:beetroot":9,"minecraft:rotten_flesh":93,"spartanshields:obsidian_tower_shield":1,"spartanweaponry:diamond_scythe":3,"minecraft:mangrove_sign":3,"alexsmobs:blood_sac":4,"minecraft:gunpowder":123,"spartanweaponry:husk_head":2,"minecraft:skeleton_skull":1,"minecraft:oak_wood":15,"minecraft:charcoal":12,"spartanweaponry:iron_javelin":3,"minecraft:spruce_pressure_plate":4,"minecraft:azalea":2,"minecraft:ladder":6,"minecraft:arrow":99,"minecraft:glass":9,"minecraft:stone_brick_stairs":1,"minecraft:quartz":37,"minecraft:netherrack":2,"minecraft:egg":1,"alexsmobs:mosquito_proboscis":2,"minecraft:iron_ingot":177,"minecraft:wheat_seeds":5,"minecraft:deepslate_brick_wall":5,"minecraft:cobbled_deepslate_wall":4,"minecraft:iron_helmet":6,"minecraft:cobblestone":204,"minecraft:book":9,"minecraft:salmon_bucket":1,"minecraft:amethyst_block":54,"minecraft:spruce_stairs":2,"minecraft:coal":3,"minecraft:diorite":7,"minecraft:torch":130,"luckys_armory:heavy_iron_armor_helmet":1,"minecraft:nether_wart_block":9,"minecraft:rose_bush":2,"minecraft:zombie_head":8,"minecraft:diamond_helmet":2,"minecraft:potion":3,"minecraft:iron_leggings":3,"minecraft:white_banner":1,"minecraft:chainmail_leggings":1,"minecraft:tripwire_hook":2,"tconstruct:swasher":2,"minecraft:gray_carpet":1,"minecraft:dandelion":1,"minecraft:stone_brick_slab":1,"minecraft:smooth_basalt":5,"minecraft:redstone":52,"spartanweaponry:iron_battle_hammer":1,"minecraft:soul_soil":12,"minecraft:dark_oak_sign":1,"minecraft:smooth_stone_slab":1,"spartanweaponry:iron_scythe":2,"minecraft:tuff":3,"minecraft:stone_shovel":1,"minecraft:clay_ball":36,"spartanshields:diamond_basic_shield":3,"minecraft:iron_boots":2,"luckys_armory:heavy_iron_armor_boots":1,"luckys_armory:heavy_iron_armor_chestplate":1,"minecraft:oak_sign":1,"minecraft:glass_pane":8,"minecraft:flint_and_steel":1,"minecraft:filled_map":4,"spartanweaponry:enderman_head":2,"minecraft:stone":45,"minecraft:peony":6,"minecraft:iron_chestplate":3,"minecraft:andesite":1,"minecraft:mossy_stone_bricks":1,"minecraft:oak_sapling":2,"minecraft:spider_eye":1,"minecraft:birch_sign":1,"minecraft:stone_bricks":4,"minecraft:birch_boat":3,"minecraft:sandstone":2,"sophisticatedbackpacks:copper_backpack":1,"minecraft:bow":1,"minecraft:calcite":7,"spartanweaponry:diamond_longbow":2,"minecraft:brick":2},"minecraft:killed_by":{"minecraft:ghast":1,"minecraft:wither_skeleton":1,"minecraft:creeper":1,"man:managgresive":1,"minecraft:husk":2,"minecraft:skeleton":9,"alexsmobs:crimson_mosquito":8},"minecraft:killed":{"minecraft:witch":1,"minecraft:spider":8,"minecraft:skeleton":70,"minecraft:illusioner":7,"minecraft:piglin":4,"minecraft:zombie_villager":3,"minecraft:creeper":11,"alexsmobs:crimson_mosquito":33,"mowziesmobs:lantern":1,"minecraft:sheep":3,"minecraft:pillager":1,"minecraft:donkey":1,"minecraft:zombie":47,"minecraft:blaze":18,"minecraft:cow":1,"minecraft:vindicator":19,"minecraft:phantom":1,"minecraft:drowned":11,"minecraft:husk":9,"minecraft:frog":1,"minecraft:hoglin":4,"minecraft:squid":5,"minecraft:wither_skeleton":3,"minecraft:enderman":4},"minecraft:broken":{"minecraft:diamond_pickaxe":1,"minecraft:wooden_sword":1,"minecraft:shield":1,"minecraft:iron_axe":1},"minecraft:mined":{"minecraft:dark_oak_planks":19,"minecraft:large_amethyst_bud":3,"minecraft:spruce_planks":12,"minecraft:white_bed":19,"minecraft:sculk_vein":1,"minecraft:granite":22,"minecraft:deepslate_tile_wall":10,"minecraft:grass_block":9,"minecraft:deepslate_bricks":8,"minecraft:soul_soil":11,"minecraft:smooth_stone":1,"minecraft:spawner":12,"spartanweaponry:enderman_wall_head":1,"minecraft:weeping_vines_plant":4,"minecraft:magma_block":2,"minecraft:iron_ore":22,"minecraft:barrel":20,"minecraft:fire":21,"minecraft:cobbled_deepslate":22,"minecraft:deepslate_lapis_ore":6,"minecraft:stripped_dark_oak_wood":1,"minecraft:enchanting_table":3,"minecraft:oak_sign":1,"minecraft:small_amethyst_bud":2,"minecraft:spruce_pressure_plate":5,"minecraft:birch_wall_sign":1,"minecraft:white_banner":1,"minecraft:deepslate_redstone_ore":25,"spartanweaponry:enderman_head":6,"minecraft:blackstone":17,"minecraft:kelp_plant":1,"minecraft:crimson_nylium":1,"minecraft:smoker":1,"minecraft:deepslate_brick_wall":4,"minecraft:soul_fire":1,"minecraft:amethyst_cluster":11,"minecraft:soul_lantern":29,"minecraft:torch":6,"minecraft:blast_furnace":3,"minecraft:calcite":2,"minecraft:chest":9,"minecraft:nether_quartz_ore":90,"minecraft:cobblestone":8,"minecraft:cyan_bed":2,"minecraft:oak_planks":6,"minecraft:damaged_anvil":1,"minecraft:wall_torch":28,"minecraft:amethyst_block":1,"minecraft:skeleton_skull":1,"minecraft:chain":6,"minecraft:nether_wart_block":15,"minecraft:tinted_glass":4,"minecraft:birch_log":41,"minecraft:jukebox":3,"minecraft:stone_brick_stairs":1,"minecraft:yellow_glazed_terracotta":1,"minecraft:smooth_stone_slab":1,"minecraft:grass":8,"minecraft:oak_log":1,"minecraft:dirt":19,"minecraft:sand":70,"minecraft:wither_skeleton_skull":1,"minecraft:crimson_planks":2,"spartanweaponry:spider_wall_head":4,"minecraft:smooth_basalt":2,"minecraft:deepslate":268,"minecraft:stonecutter":2,"minecraft:netherrack":229,"minecraft:stripped_crimson_stem":1,"minecraft:cyan_candle":23,"minecraft:oak_leaves":9,"minecraft:suspicious_gravel":2,"minecraft:nether_gold_ore":18,"minecraft:deepslate_tiles":35,"minecraft:tuff":19,"spartanweaponry:spider_head":2,"minecraft:potted_wither_rose":1,"minecraft:deepslate_diamond_ore":30,"minecraft:cobbled_deepslate_slab":5,"gravestone:gravestone":26,"minecraft:ladder":6,"minecraft:chiseled_bookshelf":4,"minecraft:black_banner":8,"minecraft:crimson_roots":3,"minecraft:weeping_vines":1,"minecraft:kelp":1,"minecraft:sandstone":4,"minecraft:crimson_stem":27,"minecraft:hay_block":23,"minecraft:black_stained_glass_pane":4,"minecraft:oak_trapdoor":13,"minecraft:furnace":6,"minecraft:peony":1,"minecraft:bookshelf":40,"minecraft:potatoes":556,"minecraft:deepslate_iron_ore":83,"minecraft:lantern":12,"minecraft:stone":36,"minecraft:bone_block":24,"minecraft:cake":1,"minecraft:glass_pane":1,"minecraft:soul_sand":19,"minecraft:red_banner":3,"minecraft:crafting_table":8,"minecraft:cobbled_deepslate_wall":6,"minecraft:rose_bush":10,"minecraft:stone_slab":6,"minecraft:tall_grass":1,"minecraft:deepslate_gold_ore":25,"minecraft:sculk":3,"minecraft:diorite":5,"minecraft:spruce_stairs":1,"minecraft:birch_planks":1,"minecraft:black_stained_glass":2,"minecraft:black_wall_banner":9,"minecraft:birch_leaves":2,"minecraft:white_wall_banner":1,"securitycraft:reinforced_stone":8,"minecraft:coal_ore":94,"minecraft:dark_oak_sign":1,"minecraft:cyan_carpet":74,"minecraft:zombie_head":1,"minecraft:flower_pot":2,"minecraft:gravel":15,"minecraft:birch_sign":3,"minecraft:stone_bricks":1,"minecraft:mossy_stone_bricks":1},"minecraft:picked_up":{"minecraft:birch_door":2,"minecraft:iron_chestplate":1,"minecraft:creeper_head":2,"minecraft:flower_pot":3,"minecraft:stone_slab":6,"minecraft:enchanted_book":1,"minecraft:wither_rose":1,"minecraft:potion":4,"minecraft:stone_brick_stairs":1,"spartanshields:diamond_basic_shield":2,"minecraft:crimson_planks":2,"minecraft:amethyst_block":31,"minecraft:music_disc_cat":5,"minecraft:string":13,"minecraft:soul_soil":12,"minecraft:cooked_salmon":1,"minecraft:smooth_stone_slab":1,"minecraft:iron_leggings":2,"minecraft:armor_stand":5,"minecraft:zombie_head":13,"minecraft:smooth_stone":1,"minecraft:oak_sign":1,"minecraft:cherry_boat":2,"alexsmobs:blood_sac":25,"minecraft:deepslate_tiles":35,"minecraft:gold_nugget":70,"minecraft:cobbled_deepslate":364,"minecraft:spruce_planks":12,"minecraft:rose_bush":9,"spartanweaponry:diamond_rapier":3,"minecraft:calcite":5,"minecraft:azalea":2,"minecraft:iron_pickaxe":1,"spartanweaponry:drowned_head":1,"minecraft:deepslate_tile_wall":10,"minecraft:melon_slice":13,"immersive_armors:steampunk_chestplate":1,"minecraft:iron_boots":2,"minecraft:furnace":6,"minecraft:golden_helmet":1,"minecraft:spruce_pressure_plate":5,"minecraft:stick":40,"minecraft:jukebox":3,"minecraft:deepslate_brick_wall":7,"minecraft:oak_fence":10,"minecraft:torch":101,"minecraft:spruce_stairs":3,"minecraft:porkchop":4,"minecraft:diorite":32,"minecraft:rotten_flesh":94,"minecraft:salmon_bucket":1,"minecraft:blaze_rod":9,"minecraft:cobblestone":391,"alexsmobs:flying_fish":1,"spartanweaponry:diamond_longbow":2,"minecraft:birch_log":57,"minecraft:enchanting_table":3,"minecraft:magma_block":2,"minecraft:andesite":1,"minecraft:smoker":1,"minecraft:potato":2029,"minecraft:flint":9,"minecraft:tuff":21,"minecraft:wither_skeleton_skull":2,"minecraft:lapis_lazuli":42,"minecraft:dirt":287,"minecraft:lantern":10,"minecraft:bone":89,"minecraft:stonecutter":2,"minecraft:bow":3,"minecraft:wheat_seeds":5,"minecraft:cobbled_deepslate_wall":5,"minecraft:raw_gold":25,"minecraft:cobbled_deepslate_slab":5,"spartanweaponry:enderman_head":10,"minecraft:dark_oak_sign":1,"minecraft:mossy_stone_bricks":1,"minecraft:cyan_candle":68,"securitycraft:reinforced_iron_trapdoor":1,"minecraft:oak_planks":18,"minecraft:stone_hoe":1,"tconstruct:necrotic_bone":3,"spartanweaponry:iron_saber":1,"minecraft:music_disc_13":1,"minecraft:poisonous_potato":11,"minecraft:stripped_crimson_stem":1,"minecraft:sand":103,"sophisticatedbackpacks:iron_backpack":2,"minecraft:ink_sac":11,"securitycraft:reinforced_stone":8,"minecraft:cyan_bed":6,"minecraft:dark_oak_log":4,"minecraft:barrel":20,"spartanshields:obsidian_tower_shield":3,"minecraft:diamond":64,"minecraft:soul_lantern":30,"minecraft:granite":18,"minecraft:golden_apple":1,"minecraft:golden_horse_armor":1,"minecraft:emerald":8,"alexsmobs:maggot":1,"minecraft:oak_sapling":2,"minecraft:netherrack":205,"minecraft:crimson_roots":2,"minecraft:diamond_pickaxe":1,"minecraft:fishing_rod":1,"minecraft:crafting_table":9,"minecraft:ladder":12,"spartanweaponry:husk_head":2,"minecraft:diamond_horse_armor":1,"gravestone:obituary":17,"minecraft:chain":6,"minecraft:shield":1,"minecraft:oak_trapdoor":13,"minecraft:flint_and_steel":4,"minecraft:item_frame":2,"minecraft:cyan_carpet":114,"minecraft:blackstone":17,"spartanweaponry:iron_quarterstaff":1,"minecraft:beef":1,"minecraft:oak_boat":3,"minecraft:tinted_glass":4,"minecraft:sugar_cane":7,"minecraft:chest":10,"minecraft:birch_sapling":1,"minecraft:egg":5,"minecraft:phantom_membrane":1,"minecraft:raw_iron":104,"minecraft:sandstone":7,"minecraft:oak_door":2,"minecraft:cake":2,"minecraft:mangrove_sign":3,"spartanweaponry:spider_head":8,"minecraft:carrot":1,"minecraft:redstone":90,"minecraft:iron_horse_armor":1,"minecraft:dark_oak_planks":23,"minecraft:arrow":155,"minecraft:weeping_vines":1,"minecraft:stone_shovel":2,"spartanweaponry:illager_head":6,"minecraft:pumpkin_pie":15,"minecraft:peony":2,"minecraft:shears":1,"minecraft:deepslate_bricks":8,"minecraft:hay_block":23,"immersive_armors:warrior_chestplate":1,"minecraft:gold_ingot":62,"minecraft:saddle":2,"sophisticatedbackpacks:copper_backpack":1,"minecraft:black_banner":17,"minecraft:mutton":8,"minecraft:skeleton_skull":12,"minecraft:white_wool":49,"minecraft:bone_block":24,"minecraft:rail":8,"minecraft:stripped_oak_log":1,"minecraft:tripwire_hook":1,"minecraft:crimson_stem":27,"minecraft:leather":5,"minecraft:birch_planks":29,"minecraft:filled_map":3,"minecraft:oak_log":12,"minecraft:chainmail_chestplate":1,"minecraft:yellow_glazed_terracotta":1,"minecraft:golden_boots":1,"minecraft:gunpowder":60,"minecraft:nether_wart_block":21,"tconstruct:swasher":2,"minecraft:cobblestone_stairs":2,"spartanweaponry:diamond_scythe":2,"alexsmobs:mosquito_proboscis":6,"minecraft:white_banner":3,"minecraft:piglin_head":2,"minecraft:red_carpet":6,"minecraft:gray_carpet":4,"minecraft:stone_bricks":4,"minecraft:kelp":1,"minecraft:iron_ingot":138,"minecraft:glass_bottle":4,"minecraft:soul_sand":20,"minecraft:dark_oak_stairs":6,"minecraft:book":162,"minecraft:smooth_basalt":2,"minecraft:dark_oak_slab":1,"spartanweaponry:iron_scythe":2,"minecraft:birch_boat":2,"minecraft:chiseled_stone_bricks":1,"minecraft:stone_brick_slab":1,"minecraft:quartz":88,"minecraft:dandelion":1,"minecraft:gravel":13,"spartanweaponry:blaze_head":3,"minecraft:amethyst_shard":40,"minecraft:red_banner":3,"minecraft:blast_furnace":3,"minecraft:white_bed":19,"minecraft:spider_eye":5,"minecraft:leather_helmet":1,"minecraft:oak_wood":20,"minecraft:chainmail_leggings":1,"minecraft:iron_helmet":3,"minecraft:painting":2,"minecraft:birch_sign":4,"minecraft:gray_wool":2,"minecraft:baked_potato":294,"minecraft:damaged_anvil":1,"minecraft:coal":125},"minecraft:crafted":{"minecraft:black_dye":10,"easy_hammers:iron_hammer":1,"minecraft:oak_planks":40,"minecraft:barrel":3,"spartanweaponry:iron_scythe":1,"minecraft:birch_boat":3,"minecraft:chain":10,"spartanshields:wooden_tower_shield":1,"minecraft:loom":1,"securitycraft:keypad_item":1,"luckys_armory:heavy_iron_armor_boots":1,"minecraft:heavy_weighted_pressure_plate":1,"minecraft:dark_oak_door":3,"securitycraft:laser_block":1,"minecraft:glass":35,"spartanshields:obsidian_tower_shield":4,"minecraft:diamond_helmet":1,"minecraft:iron_boots":1,"luckys_armory:heavy_diamond_armor_boots":1,"minecraft:chest":1,"luckys_armory:heavy_diamond_armor_leggings":1,"minecraft:smoker":1,"minecraft:white_banner":1,"minecraft:oak_slab":12,"spartanweaponry:diamond_scythe":1,"minecraft:crafting_table":3,"securitycraft:reinforced_stone_button":8,"minecraft:iron_helmet":4,"minecraft:baked_potato":250,"securitycraft:universal_owner_changer":1,"minecraft:red_wool":6,"luckys_armory:heavy_iron_armor_chestplate":1,"minecraft:birch_planks":32,"minecraft:creeper_banner_pattern":1,"luckys_armory:heavy_iron_armor_helmet":1,"minecraft:iron_chestplate":2,"minecraft:diamond_pickaxe":1,"minecraft:stick":32,"minecraft:iron_ingot":104,"minecraft:iron_pickaxe":1,"minecraft:iron_block":3,"minecraft:stone_sword":1,"luckys_armory:heavy_diamond_armor_chestplate":1,"minecraft:gold_ingot":25,"minecraft:shears":1,"securitycraft:universal_block_reinforcer_lvl1":1,"minecraft:wooden_sword":1,"luckys_armory:heavy_iron_armor_leggings":1,"minecraft:iron_nugget":27,"minecraft:tinted_glass":4,"minecraft:red_banner":1,"minecraft:bone_meal":3,"spartanweaponry:iron_javelin":2,"minecraft:oak_trapdoor":6,"minecraft:glass_pane":48,"minecraft:flint_and_steel":1,"minecraft:iron_axe":1,"minecraft:ladder":18,"securitycraft:universal_block_remover":1,"minecraft:deepslate_tile_wall":10,"minecraft:redstone_block":1,"minecraft:dark_oak_planks":16,"minecraft:birch_sign":3,"minecraft:red_dye":6,"minecraft:crimson_planks":92,"minecraft:skull_banner_pattern":1,"minecraft:iron_trapdoor":1,"securitycraft:universal_block_modifier":1,"spartanweaponry:pole":4,"minecraft:air":0,"minecraft:white_wool":4,"luckys_armory:heavy_diamond_armor_helmet":1,"minecraft:golden_apple":3,"minecraft:white_dye":3,"minecraft:black_stained_glass_pane":32,"minecraft:iron_leggings":1,"minecraft:stonecutter":1,"minecraft:anvil":1,"minecraft:torch":76}},"DataVersion":3465}